hurry/__init__.py
hurry/main.py
hurry/utils.py
hurry_script-0.2.dist-info/DESCRIPTION.rst
hurry_script-0.2.dist-info/METADATA
hurry_script-0.2.dist-info/RECORD
hurry_script-0.2.dist-info/WHEEL
hurry_script-0.2.dist-info/entry_points.txt
hurry_script-0.2.dist-info/metadata.json
hurry_script-0.2.dist-info/top_level.txt
