Metadata-Version: 2.0
Name: hurry-script
Version: 0.2
Summary: Hurry! helps you run your routine commands and scripts faster.
Home-page: UNKNOWN
Author: Roman Telichkin
Author-email: roman@telichk.in
License: UNKNOWN
Platform: UNKNOWN
Requires-Dist: docopt (==0.6.2)
Requires-Dist: py (==1.4.34)
